{
  "case_uid": "test/intermediate_algebra/558.json",
  "dataset_idx": 103,
  "source": "failed",
  "l_value": 10,
  "cut_idx": 310,
  "judge": {
    "parsed_ok": true,
    "raw_output": "{\n  \"truthfulness\": {\"label\": \"F\", \"reason\": \"一开头就说“标准答案显示范围是(3,4]”，明显是站在已知答案后倒推，不像前文自然推演。\"},\n  \"coherence\": {\"label\": \"F\", \"reason\": \"前文还停留在尝试代值与一般分析，修复后续却突然引入“分解后二次方程”“判别式为…”，关键结论缺少承接。\"},\n  \"correctness\": {\"label\": \"M\", \"reason\": \"主方向与标准解一致，但表述里把判别式非负简化成“当λ≥3时”忽略了λ=0，且若干结论只是提示未论证完整。\"},\n  \"progress\": {\"label\": \"T\", \"reason\": \"相比原始后续的重复徘徊，修复后续明确转向因式分解、判别式、边界值与区间检验，更接近正确解法。\"},\n  \"non_leakage\": {\"label\": \"F\", \"reason\": \"直接泄露“标准答案显示范围是(3,4]”，并几乎给出整套标准题解的骨架，暴露过度。\"}\n}",
    "metrics": {
      "truthfulness": {
        "label": "F",
        "reason": "一开头就说“标准答案显示范围是(3,4]”，明显是站在已知答案后倒推，不像前文自然推演。"
      },
      "coherence": {
        "label": "F",
        "reason": "前文还停留在尝试代值与一般分析，修复后续却突然引入“分解后二次方程”“判别式为…”，关键结论缺少承接。"
      },
      "correctness": {
        "label": "M",
        "reason": "主方向与标准解一致，但表述里把判别式非负简化成“当λ≥3时”忽略了λ=0，且若干结论只是提示未论证完整。"
      },
      "progress": {
        "label": "T",
        "reason": "相比原始后续的重复徘徊，修复后续明确转向因式分解、判别式、边界值与区间检验，更接近正确解法。"
      },
      "non_leakage": {
        "label": "F",
        "reason": "直接泄露“标准答案显示范围是(3,4]”，并几乎给出整套标准题解的骨架，暴露过度。"
      }
    },
    "attempts_used": 1
  }
}