{
  "case_uid": "test/prealgebra/1139.json",
  "dataset_idx": 9,
  "source": "failed",
  "l_value": 5,
  "cut_idx": 275,
  "judge": {
    "parsed_ok": true,
    "raw_output": "{\n  \"truthfulness\": {\n    \"label\": \"M\",\n    \"reason\": \"前文确实已经开始怀疑很多情形是“多用了加号”而不合法，因此转向检查唯一加号的结合位置是自然的；但“只剩四种有效方式”的收束过于干净，略像事后倒推。\"\n  },\n  \"coherence\": {\n    \"label\": \"T\",\n    \"reason\": \"它直接回应了前文最大症结：前面枚举了许多非法或重复情况，修复后续先用乘法结合律去重，再用“只允许一个加号”筛合法性，衔接自然。\"\n  },\n  \"correctness\": {\n    \"label\": \"T\",\n    \"reason\": \"修复后续的核心判断是对的：乘法内部怎么加括号不影响结果，关键只在于+1与多少个连续乘法因子结合，最终确实只有4种不同值。\"\n  },\n  \"progress\": {\n    \"label\": \"T\",\n    \"reason\": \"相比原始后续继续无序枚举并混入非法表达式，修复后续明确建立了正确分类原则，显著推进到正确解法。\"\n  },\n  \"non_leakage\": {\n    \"label\": \"F\",\n    \"reason\": \"它几乎直接给出了标准题解的核心结构和最终结论“只有四种有效方式”，暴露程度较高，不太像仍在自然探索中的中间思路。\"\n  }\n}",
    "metrics": {
      "truthfulness": {
        "label": "M",
        "reason": "前文确实已经开始怀疑很多情形是“多用了加号”而不合法，因此转向检查唯一加号的结合位置是自然的；但“只剩四种有效方式”的收束过于干净，略像事后倒推。"
      },
      "coherence": {
        "label": "T",
        "reason": "它直接回应了前文最大症结：前面枚举了许多非法或重复情况，修复后续先用乘法结合律去重，再用“只允许一个加号”筛合法性，衔接自然。"
      },
      "correctness": {
        "label": "T",
        "reason": "修复后续的核心判断是对的：乘法内部怎么加括号不影响结果，关键只在于+1与多少个连续乘法因子结合，最终确实只有4种不同值。"
      },
      "progress": {
        "label": "T",
        "reason": "相比原始后续继续无序枚举并混入非法表达式，修复后续明确建立了正确分类原则，显著推进到正确解法。"
      },
      "non_leakage": {
        "label": "F",
        "reason": "它几乎直接给出了标准题解的核心结构和最终结论“只有四种有效方式”，暴露程度较高，不太像仍在自然探索中的中间思路。"
      }
    },
    "attempts_used": 1
  }
}