{
  "case_uid": "test/prealgebra/1139.json",
  "dataset_idx": 9,
  "source": "failed",
  "l_value": 10,
  "cut_idx": 200,
  "judge": {
    "parsed_ok": true,
    "raw_output": "{\n  \"truthfulness\": {\n    \"label\": \"F\",\n    \"reason\": \"直接引用“标准答案只列出四种可能值”，明显像已知完整解答后的回看，不像前文自然推演出的思考。\"\n  },\n  \"coherence\": {\n    \"label\": \"M\",\n    \"reason\": \"它确实回应了前文枚举过多、可能有误的问题，但突然引入“标准答案”这一外部信息，衔接感被削弱。\"\n  },\n  \"correctness\": {\n    \"label\": \"T\",\n    \"reason\": \"核心修正方向正确：利用乘法结合律，真正不同的情况只在于把“+1”与多少个末尾因子结合，最终确为4种值。\"\n  },\n  \"progress\": {\n    \"label\": \"T\",\n    \"reason\": \"相比原始后续继续错误扩展枚举，修复后续明确收缩到合法情形并指向正确分类，明显更接近正确解法。\"\n  },\n  \"non_leakage\": {\n    \"label\": \"F\",\n    \"reason\": \"过度暴露了解题结果与结构：直接说出“标准答案”以及“四种情况”，泄露了最终解法框架。\"\n  }\n}",
    "metrics": {
      "truthfulness": {
        "label": "F",
        "reason": "直接引用“标准答案只列出四种可能值”，明显像已知完整解答后的回看，不像前文自然推演出的思考。"
      },
      "coherence": {
        "label": "M",
        "reason": "它确实回应了前文枚举过多、可能有误的问题，但突然引入“标准答案”这一外部信息，衔接感被削弱。"
      },
      "correctness": {
        "label": "T",
        "reason": "核心修正方向正确：利用乘法结合律，真正不同的情况只在于把“+1”与多少个末尾因子结合，最终确为4种值。"
      },
      "progress": {
        "label": "T",
        "reason": "相比原始后续继续错误扩展枚举，修复后续明确收缩到合法情形并指向正确分类，明显更接近正确解法。"
      },
      "non_leakage": {
        "label": "F",
        "reason": "过度暴露了解题结果与结构：直接说出“标准答案”以及“四种情况”，泄露了最终解法框架。"
      }
    },
    "attempts_used": 1
  }
}