{
  "case_uid": "test/intermediate_algebra/1981.json",
  "dataset_idx": 495,
  "source": "failed",
  "l_value": 5,
  "cut_idx": 25,
  "judge": {
    "parsed_ok": true,
    "raw_output": "{\n  \"truthfulness\": {\"label\": \"M\", \"reason\": \"像是在做收尾复核，方向自然，但表述偏清单式、元审查感较强，不太像连续自发推演。\"},\n  \"coherence\": {\"label\": \"T\", \"reason\": \"紧接前文的“再检查一遍”语境，继续核对分母、对数真数和联合解集，衔接基本自然。\"},\n  \"correctness\": {\"label\": \"T\", \"reason\": \"提到的限制条件和不等式转换都正确，没有明显数学或逻辑错误，也无自相矛盾。\"},\n  \"progress\": {\"label\": \"M\", \"reason\": \"比原始后续更系统地指出应检查的关键点，但多数只是提示复核，实际推进和新信息有限。\"},\n  \"non_leakage\": {\"label\": \"M\", \"reason\": \"虽未完整展开标准题解，但已直接点出关键结构并写出最终区间，泄露程度中等。\"}\n}",
    "metrics": {
      "truthfulness": {
        "label": "M",
        "reason": "像是在做收尾复核，方向自然，但表述偏清单式、元审查感较强，不太像连续自发推演。"
      },
      "coherence": {
        "label": "T",
        "reason": "紧接前文的“再检查一遍”语境，继续核对分母、对数真数和联合解集，衔接基本自然。"
      },
      "correctness": {
        "label": "T",
        "reason": "提到的限制条件和不等式转换都正确，没有明显数学或逻辑错误，也无自相矛盾。"
      },
      "progress": {
        "label": "M",
        "reason": "比原始后续更系统地指出应检查的关键点，但多数只是提示复核，实际推进和新信息有限。"
      },
      "non_leakage": {
        "label": "M",
        "reason": "虽未完整展开标准题解，但已直接点出关键结构并写出最终区间，泄露程度中等。"
      }
    },
    "attempts_used": 1
  }
}